gff2parquet/__init__.py
gff2parquet/cli.py
gff2parquet-0.3.0.dist-info/METADATA
gff2parquet-0.3.0.dist-info/WHEEL
gff2parquet-0.3.0.dist-info/entry_points.txt
gff2parquet-0.3.0.dist-info/licenses/LICENSE
gff2parquet-0.3.0.dist-info/RECORD
