Metadata-Version: 2.4
Name: gff2parquet
Version: 0.3.0
Summary: GFF3 cli utils (convert, merge, filter, split, print, extract)
Project-URL: Homepage, https://github.com/urineri/gff2parquet
Project-URL: Repository, https://github.com/urineri/gff2parquet.git
Author-email: Uri Neri <uri.neri@gmail.com>
License: BSD-3-Clause License
License-File: LICENSE
Requires-Python: >=3.9
Requires-Dist: polars-bio<0.19,>=0.18.0
Requires-Dist: polars<2,>=1.34.0
